quadrilateral_interpolation/__init__.py
quadrilateral_interpolation/quadinterpolator.py
quadrilateral_interpolation/test_quadinterpolator.py
quadrilateral_interpolation-1.1.1.dist-info/licenses/LICENSE
quadrilateral_interpolation-1.1.1.dist-info/METADATA
quadrilateral_interpolation-1.1.1.dist-info/WHEEL
quadrilateral_interpolation-1.1.1.dist-info/top_level.txt
quadrilateral_interpolation-1.1.1.dist-info/RECORD
