Metadata-Version: 2.4
Name: quadrilateral_interpolation
Version: 1.1.1
Summary: Fast projection of satellite images using forward quadrilateral interpolation
Author-email: Ghislain Picard <ghislain.picard@univ-grenoble-alpes.fr>
License:                   GNU LESSER GENERAL PUBLIC LICENSE
Classifier: Development Status :: 5 - Production/Stable
Classifier: Intended Audience :: Science/Research
Classifier: Topic :: Scientific/Engineering
Requires-Python: <3.14,>=3.10
License-File: LICENSE
Requires-Dist: numpy<2.5,>=2
Requires-Dist: numba<1,>=0.62.1
Requires-Dist: pyproj>=3.3.1
Requires-Dist: xarray>=2022.3.0
Provides-Extra: dev
Requires-Dist: pytest; extra == "dev"
Requires-Dist: ruff; extra == "dev"
Requires-Dist: pre-commit; extra == "dev"
Dynamic: license-file
